setup.py
mkdocs_extensions/__init__.py
mkdocs_extensions.egg-info/PKG-INFO
mkdocs_extensions.egg-info/SOURCES.txt
mkdocs_extensions.egg-info/dependency_links.txt
mkdocs_extensions.egg-info/requires.txt
mkdocs_extensions.egg-info/top_level.txt