Metadata-Version: 1.1
Name: mkdocs-extensions
Version: 0.1.2
Summary: Python mkdocs extensions
Home-page: https://github.com/duanhongyi/mkdocs-slugify
Author: Duan Hongyi
Author-email: duanhongyi@doopai.com
License: GNU GPLv3
Keywords: slugify slug transliteration russian german unicode translation flexible
Platform: UNKNOWN
Classifier: License :: OSI Approved :: GNU General Public License v3 (GPLv3)
Classifier: Programming Language :: Python
Classifier: Programming Language :: Python :: 2
Classifier: Programming Language :: Python :: 2.6
Classifier: Programming Language :: Python :: 2.7
Classifier: Programming Language :: Python :: 3
Classifier: Programming Language :: Python :: 3.3
Classifier: Programming Language :: Python :: 3.4
